testbench.sv
// Code your testbench here
// or browse Examples
`timescale 1ns / 1ps
//////////////////////////////////////////////////////////////////////////////////
// Company: 
// Module Name: smart_traffic_light_controller_tb
// Project Name: 
// Target Devices: 
// Tool Versions: 
// Description: 
// 
// Dependencies: 
// 
// Revision:
// Revision 0.01 - File Created
// Additional Comments:
// 
//////////////////////////////////////////////////////////////////////////////////

module smart_traffic_light_controller_tb;

    reg TS;
    reg TL;
    reg Clk;
    reg C;
    reg reset;

    // Outputs
    wire MR;
    wire MY;
    wire MG;
    wire SR;
    wire SY;
    wire SG;
    wire ST;

    // Instantiate the Unit Under Test (UUT)
    fsm dut (
        .MR(MR), 
        .MY(MY), 
        .MG(MG), 
        .SR(SR), 
        .SY(SY), 
        .SG(SG), 
        .ST(ST), 
        .TS(TS), 
        .TL(TL), 
        .C(C), 
        .reset(reset), 
        .Clk(Clk)
    );

    initial begin
        $dumpfile("dump.vcd");
        $dumpvars(1);

        // Initialize Inputs
        TS = 0;
        TL = 0;
        C = 0;
        reset = 1;
        Clk = 0;

        // Wait for some time
        #100;
        
        // Apply test vectors
        TS = 0; TL = 1; C = 1; reset = 0;
        #100;
        
        TS = 0; TL = 0; C = 0; reset = 1;
        #100;
        
        TS = 1; TL = 1; C = 0; reset = 0;
        #100;
        
        // End of test
        $finish;
    end

    // Clock generation
    always #50 Clk = ~Clk; // Clock period of 100ns

endmodule

design.sv
// Code your design here
`timescale 1ns / 1ps
//////////////////////////////////////////////////////////////////////////////////
// Company: 
// Engineer: vamsi
// 
// Create Date: 29.05.2023 21:42:01
// Design Name: 
// Module Name: smart_traffic_light_controller
// Project Name: 
// Target Devices: 
// Tool Versions: 
// Description: 
// 
// Dependencies: 
// 
// Revision:
// Revision 0.01 - File Created
// Additional Comments:
// 
//////////////////////////////////////////////////////////////////////////////////
// main module

module smart_traffic_light_controller(
    output MR,
    output MY,
    output MG,
    output SR,
    output SY,
    output SG,
    input reset,
    input C,
    input Clk
);

    wire TS, TL, ST;

    timer part1 (
        .TS(TS),
        .TL(TL),
        .ST(ST),
        .Clk(Clk)
    );

    fsm part2 (
        .MR(MR),
        .MY(MY),
        .MG(MG),
        .SR(SR),
        .SY(SY),
        .SG(SG),
        .ST(ST),
        .TS(TS),
        .TL(TL),
        .C(C),
        .reset(reset),
        .Clk(Clk)
    );

endmodule

// TIMER MODULE:
`timescale 1ns / 1ps

module timer(
    output TS,
    output TL,
    input ST,
    input Clk
);

    integer value;

    assign TS = (value >= 4);
    assign TL = (value >= 14);

    always @ (posedge ST or posedge Clk) begin
        if (ST == 1) begin
            value = 0;
        end else begin
            value = value + 1;
        end
    end

endmodule

// FSM MODULE
`timescale 1ns / 1ps

module fsm(
    output MR,
    output MY,
    output MG,
    output SR,
    output SY,
    output SG,
    output ST,
    input TS,
    input TL,
    input C,
    input reset,
    input Clk
);

    reg [5:0] state;
    reg ST_reg;

    parameter mainroadgreen = 6'b001100;
    parameter mainroadyellow = 6'b010100;
    parameter sideroadgreen = 6'b100001;
    parameter sideroadyellow = 6'b100010;

    assign MR = state[5];
    assign MY = state[4];
    assign MG = state[3];
    assign SR = state[2];
    assign SY = state[1];
    assign SG = state[0];
    assign ST = ST_reg;

    initial begin
        state = mainroadgreen;
        ST_reg = 0;
    end

    always @ (posedge Clk) begin
        if (reset) begin
            state = mainroadgreen;
            ST_reg = 1;
        end else begin
            ST_reg = 0;
            case (state)
                mainroadgreen: begin
                    if (TL & C) begin
                        state = mainroadyellow;
                        ST_reg = 1;
                    end
                end
                mainroadyellow: begin
                    if (TS) begin
                        state = sideroadgreen;
                        ST_reg = 1;
                    end
                end
                sideroadgreen: begin
                    if (TL | ~C) begin
                        state = sideroadyellow;
                        ST_reg = 1;
                    end
                end
                sideroadyellow: begin
                    if (TS) begin
                        state = mainroadgreen;
                        ST_reg = 1;
                    end
                end
            endcase
        end
    end

endmodule

dump.vcd
$date
	Thu May 30 08:10:22 2023
$end
$version
	Icarus Verilog
$end
$timescale
	1ps
$end
$scope module smart_traffic_light_controller $end
$var wire 1 ! C $end
$var wire 1 " Clk $end
$var wire 1 # reset $end
$var wire 1 $ TS $end
$var wire 1 % TL $end
$var wire 1 & SY $end
$var wire 1 ' ST $end
$var wire 1 ( SR $end
$var wire 1 ) SG $end
$var wire 1 * MY $end
$var wire 1 + MR $end
$var wire 1 , MG $end
$upscope $end
$scope module smart_traffic_light_controller_tb $end
$var wire 1 - SY $end
$var wire 1 . ST $end
$var wire 1 / SR $end
$var wire 1 0 SG $end
$var wire 1 1 MY $end
$var wire 1 2 MR $end
$var wire 1 3 MG $end
$var reg 1 4 C $end
$var reg 1 5 Clk $end
$var reg 1 6 TL $end
$var reg 1 7 TS $end
$var reg 1 8 reset $end
$upscope $end
$enddefinitions $end
$comment Show the parameter values. $end
$dumpall
$end
#0
$dumpvars
18
07
06
05
04
13
02
01
00
1/
0.
0-
1,
0+
0*
0)
1(
0'
0&
x%
x$
z#
z"
z!
$end
#50000
1.
15
#100000
05
08
14
16
#150000
11
03
1.
15
#200000
05
18
04
06
#250000
01
13
15
#300000
05
08
16
17
#350000
0.
15
